cn/__init__.py
cn/xyz/__init__.py
cn/xyz/versionChange/__init__.py
cn/xyz/versionChange/versionChange.py
cn.xyz.versionChangeV3-0.2.dist-info/METADATA
cn.xyz.versionChangeV3-0.2.dist-info/RECORD
cn.xyz.versionChangeV3-0.2.dist-info/WHEEL
cn.xyz.versionChangeV3-0.2.dist-info/top_level.txt
