Metadata-Version: 2.1
Name: cn.xyz.versionChangeV3
Version: 0.2
Summary: change artifact version in maven pom.xml for python3 
Home-page: UNKNOWN
Author: lvchenggang
Author-email: lvchenggang@xyz.cn
License: UNKNOWN
Platform: Independant
